{
  "Items": [
    {
      "Src": "no1.ly",
      "Edited": [
        {"Pure score with fingering": "no1_f.ly"},
        {"With articulation and dynamics": "no1_ad.ly"},
        {"With articulation, dynamics and fingering": "no1_adf.ly"}],
      "Opus": "",
      "No": "1",
      "Piecename": "Melodie",
      "Difficulty": {
        "Technique": "",
        "Delicacy": "",
        "Complexity": ""
      }
    },
    {
      "Src": "no2.ly",
      "Edited": [
        {"Source score with fingering": "no2_f.ly"},
        {"With articulation and dynamics": "no2_ad.ly"},
        {"With articulation, dynamics and fingering": "no2_adf.ly"}],
      "Opus": "",
      "No": "2",
      "Piecename": "Soldatenmarsch",
      "Difficulty": {
        "Technique": "",
        "Delicacy": "",
        "Complexity": ""
      }
    }
  ]
}